LICENSE.txt
README.md
setup.py
charylu_models.egg-info/PKG-INFO
charylu_models.egg-info/SOURCES.txt
charylu_models.egg-info/dependency_links.txt
charylu_models.egg-info/requires.txt
charylu_models.egg-info/top_level.txt
charylumodels/__init__.py
charylumodels/create_tokenized_dataset.py
charylumodels/parallel_utils.py
charylumodels/models/__init__.py
charylumodels/models/RetroMae/__init__.py
charylumodels/models/RetroMae/dataset.py
charylumodels/models/RetroMae/lightning.py
charylumodels/models/RetroMae/model.py
charylumodels/models/base_decoder/__init__.py
charylumodels/models/base_decoder/model.py
charylumodels/models/base_encoder/__init__.py
charylumodels/models/base_encoder/lightning.py
charylumodels/models/base_encoder/model.py
charylumodels/models/conformer/__init__.py
charylumodels/models/conformer/model.py
charylumodels/models/vanilla/__init__.py
charylumodels/models/vanilla/encoder.py
charylumodels/models/vanilla/encoder_lightining.py
charylumodels/transformer/__init__.py
charylumodels/transformer/activations.py
charylumodels/transformer/attention.py
charylumodels/transformer/attention_blocks.py
charylumodels/transformer/mlm_generation.py
charylumodels/transformer/norm.py
charylumodels/transformer/rotary.py
charylumodels/transformer/schedulers.py
charylumodels/transformer/text_generation.py
charylumodels/transformer/transformer_blocks.py
charylumodels/transformer/utils.py