Metadata-Version: 2.4
Name: charylu-models
Version: 0.0.6
Summary: Biblioteca de modelos implemantados por Luis Chary
Author: Luis Felipe Chary
License-File: LICENSE.txt
Requires-Dist: numpy<=1.26.4
Requires-Dist: charylu-tokenizer==0.0.6
Requires-Dist: tqdm
Requires-Dist: torch<=2.3.1
Requires-Dist: wheel
Requires-Dist: bitsandbytes<=0.43.1
Requires-Dist: packaging<=24.1
Requires-Dist: ninja<=1.11.1.1
Requires-Dist: torchmetrics<=1.4.0.post0
Requires-Dist: deepspeed<=0.14.4
Provides-Extra: lightning
Requires-Dist: lightning<=2.3.0; extra == "lightning"
Dynamic: author
Dynamic: description
Dynamic: description-content-type
Dynamic: license-file
Dynamic: provides-extra
Dynamic: requires-dist
Dynamic: summary
